README.md
setup.py
relays_manager/__init__.py
relays_manager.egg-info/PKG-INFO
relays_manager.egg-info/SOURCES.txt
relays_manager.egg-info/dependency_links.txt
relays_manager.egg-info/requires.txt
relays_manager.egg-info/top_level.txt