Metadata-Version: 1.0
Name: relays-manager
Version: 0.0.1
Summary: A Python library to interact with ICStation USB relays.
Home-page: https://github.com/M-Gregoire/relays_manager
Author: Grégoire Martinache
Author-email: UNKNOWN
License: UNKNOWN
Keywords: relays
Platform: UNKNOWN
